cllm/__init__.py
cllm/cli.py
llmctl-0.1.8.dist-info/licenses/LICENSE
llmctl-0.1.8.dist-info/METADATA
llmctl-0.1.8.dist-info/WHEEL
llmctl-0.1.8.dist-info/entry_points.txt
llmctl-0.1.8.dist-info/top_level.txt
llmctl-0.1.8.dist-info/RECORD
