Metadata-Version: 2.4
Name: llmctl
Version: 0.1.8
Summary: A professional CLI tool for interacting with OpenAI and Anthropic LLMs with cost tracking
Home-page: https://github.com/sabbiramin113008/llmctl
Author: SM Sabbir Amin
Author-email: SM Sabbir Amin <sabbiramin.cse11ruet@gmail.com>
License: MIT
Project-URL: Homepage, https://github.com/sabbiramin113008/llmctl
Project-URL: Bug Reports, https://github.com/sabbiramin113008/llmctl/issues
Project-URL: Source, https://github.com/sabbiramin113008/llmctl
Keywords: llm,cli,openai,anthropic,claude,gpt,cost-tracking,terminal
Classifier: Development Status :: 4 - Beta
Classifier: Intended Audience :: Developers
Classifier: Topic :: Software Development :: Libraries :: Python Modules
Classifier: License :: OSI Approved :: MIT License
Classifier: Programming Language :: Python :: 3
Classifier: Programming Language :: Python :: 3.7
Classifier: Programming Language :: Python :: 3.8
Classifier: Programming Language :: Python :: 3.9
Classifier: Programming Language :: Python :: 3.10
Classifier: Programming Language :: Python :: 3.11
Classifier: Programming Language :: Python :: 3.12
Classifier: Operating System :: OS Independent
Classifier: Environment :: Console
Requires-Python: >=3.7
License-File: LICENSE
Requires-Dist: openai>=1.0.0
Requires-Dist: anthropic>=0.18.0
Requires-Dist: colorama>=0.4.6
Dynamic: author
Dynamic: home-page
Dynamic: license-file
Dynamic: requires-python
